agent.py
components.py
example.py
genetic.py
qlearn.py
simulation.py
utils.py
vector2d.py
vehicle.py
pysimulate-1.1.7.dist-info/METADATA
pysimulate-1.1.7.dist-info/WHEEL
pysimulate-1.1.7.dist-info/top_level.txt
pysimulate-1.1.7.dist-info/RECORD
