Metadata-Version: 2.1
Name: pysimulate
Version: 1.1.7
Summary: AI Track Simulator is an easy-to-use Simulator engine built in pygame
Home-page: https://github.com/lukeharwood11/ai-racecar-simulator
Author: Luke Harwood
Author-email: mwstudiodev@gmail.com
License: MIT
Keywords: simulator ai-gym racecar
Platform: UNKNOWN
Requires-Python: >=3.6
Requires-Dist: numpy (>=1.22.4)
Requires-Dist: pygame (>=2.1.2)
Requires-Dist: sklearn
Requires-Dist: scikit-learn (>=1.1.2)
Requires-Dist: tensorflow (>=2.7.0)
Requires-Dist: keras (>=2.7.0)
